{
  "source_file": "/Users/devin/repos/projects/data-pipelines/boxrec_scraper/data/raw/boxrec_html/en_box-pro_834487.html",
  "extracted_at": "2025-08-01T16:43:18.835062",
  "id": "",
  "boxrec_id": "834487",
  "boxrec_url": "https://boxrec.com/en/box-pro/834487",
  "boxrec_wiki_url": "https://boxrec.com/wiki/index.php?title=Human:834487",
  "slug": "bakhodir-jalolov",
  "name": "Bakhodir Jalolov",
  "birth_name": "Bakhodir Isomiddin Ugli Jalolov",
  "nicknames": "\"The Big Uzbek\"",
  "avatar_image": "https://boxrec.com/images/thumb/2/2f/834487.jpg/200px-834487.jpg",
  "residence": "Indio, California, USA",
  "birth_place": "Sariosiyo, Uzbekistan",
  "birth_date": null,
  "gender": "M",
  "nationality": "Uzbekistan",
  "height": "201",
  "reach": "206",
  "stance": "southpaw",
  "bio": "",
  "promoters": "",
  "trainers": "",
  "managers": "",
  "gym": null,
  "pro_debut_date": "",
  "pro_division": "heavy",
  "pro_wins": 15,
  "pro_wins_by_knockout": 14,
  "pro_losses": 0,
  "pro_losses_by_knockout": 0,
  "pro_draws": 0,
  "pro_status": "",
  "pro_total_bouts": 15,
  "pro_total_rounds": null,
  "amateur_debut_date": "",
  "amateur_division": "",
  "amateur_wins": null,
  "amateur_wins_by_knockout": null,
  "amateur_losses": null,
  "amateur_losses_by_knockout": null,
  "amateur_draws": null,
  "amateur_status": "inactive",
  "amateur_total_bouts": null,
  "amateur_total_rounds": null,
  "bouts": [
    {
      "date": "Apr 25",
      "opponent_name": "Ihor Shevadzutskyi",
      "opponent_id": "856426",
      "opponent_url": "https://boxrec.com/en/box-pro/856426",
      "opponent_record": "12-2-0",
      "recent_form": "WWLWLW",
      "venue": "Barys Arena, Astana",
      "result": "win",
      "rating": 1,
      "event_link": "https://boxrec.com/en/event/915006",
      "bout_link": "https://boxrec.com/en/event/915006/3309647"
    },
    {
      "date": "Nov 23",
      "opponent_name": "Chris Thompson",
      "opponent_id": "801317",
      "opponent_url": "https://boxrec.com/en/box-pro/801317",
      "opponent_record": "12-5-1",
      "recent_form": "WDWLLL",
      "venue": "Humo Arena, Tashkent",
      "result": "win",
      "rating": 1,
      "event_link": "https://boxrec.com/en/event/883795",
      "bout_link": "https://boxrec.com/en/event/883795/3067304"
    },
    {
      "date": "Aug 23",
      "opponent_name": "Onoriode Ehwarieme",
      "opponent_id": "555940",
      "opponent_url": "https://boxrec.com/en/box-pro/555940",
      "opponent_record": "20-2-0",
      "recent_form": "WLWLWW",
      "venue": "Hard Rock Hotel & Casino, Tulsa",
      "result": "win",
      "rating": 1,
      "event_link": "https://boxrec.com/en/event/877061",
      "bout_link": "https://boxrec.com/en/event/877061/3008614"
    },
    {
      "date": "Nov 22",
      "opponent_name": "Curtis Harper",
      "opponent_id": "528952",
      "opponent_url": "https://boxrec.com/en/box-pro/528952",
      "opponent_record": "14-7-0",
      "recent_form": "LWLLW",
      "venue": "Dignity Health Sports Park, Carson",
      "result": "win",
      "rating": 1,
      "event_link": "https://boxrec.com/en/event/863038",
      "bout_link": "https://boxrec.com/en/event/863038/2908087"
    },
    {
      "date": "Jun 22",
      "opponent_name": "Jack Mulowayi",
      "opponent_id": "735878",
      "opponent_url": "https://boxrec.com/en/box-pro/735878",
      "opponent_record": "11-2-1",
      "recent_form": "WLWWWW",
      "venue": "Turning Stone Resort & Casino, Verona",
      "result": "win",
      "rating": 2,
      "event_link": "https://boxrec.com/en/event/854120",
      "bout_link": "https://boxrec.com/en/event/854120/2835095"
    },
    {
      "date": "Mar 22",
      "opponent_name": "Kamil Sokolowski",
      "opponent_id": "698269",
      "opponent_url": "https://boxrec.com/en/box-pro/698269",
      "opponent_record": "11-25-2",
      "recent_form": "LLLWLL",
      "venue": "Duty Free Tennis Stadium, Dubai",
      "result": "win",
      "rating": 1,
      "event_link": "https://boxrec.com/en/event/847995",
      "bout_link": "https://boxrec.com/en/event/847995/2811545"
    },
    {
      "date": "Dec 21",
      "opponent_name": "Julio Cesar \nCalimeno",
      "opponent_id": "850609",
      "opponent_url": "https://boxrec.com/en/box-pro/850609",
      "opponent_record": "4-1-0",
      "recent_form": "WWWWL",
      "venue": "Coca-Cola Arena, Dubai",
      "result": "win",
      "rating": 1,
      "event_link": "https://boxrec.com/en/event/842712",
      "bout_link": "https://boxrec.com/en/event/842712/2761089"
    },
    {
      "date": "Apr 21",
      "opponent_name": "Kristaps Zutis",
      "opponent_id": "695273",
      "opponent_url": "https://boxrec.com/en/box-pro/695273",
      "opponent_record": "7-1-2",
      "recent_form": "WWWWW",
      "venue": "Humo Arena, Tashkent",
      "result": "win",
      "event_link": "https://boxrec.com/en/event/830156",
      "bout_link": "https://boxrec.com/en/event/830156/2653315"
    },
    {
      "date": "Dec 20",
      "opponent_name": "Wilfrido Leal",
      "opponent_id": "327859",
      "opponent_url": "https://boxrec.com/en/box-pro/327859",
      "opponent_record": "10-17-3",
      "recent_form": "LLLDLL",
      "venue": "San Luis Rio Colorado",
      "result": "win",
      "event_link": "https://boxrec.com/en/event/823282",
      "bout_link": "https://boxrec.com/en/event/823282/2602933"
    },
    {
      "date": "Apr 19",
      "opponent_name": "Brendan Barrett",
      "opponent_id": "491140",
      "opponent_url": "https://boxrec.com/en/box-pro/491140",
      "opponent_record": "7-2-2",
      "recent_form": "WWWWLL",
      "venue": "Sony Hall, New York",
      "result": "win",
      "rating": 1,
      "event_link": "https://boxrec.com/en/event/785258",
      "bout_link": "https://boxrec.com/en/event/785258/2337485"
    },
    {
      "date": "Mar 19",
      "opponent_name": "Willie Harvey",
      "opponent_id": "724554",
      "opponent_url": "https://boxrec.com/en/box-pro/724554",
      "opponent_record": "3-1-1",
      "recent_form": "DWWLW",
      "venue": "Marconi Automative Museum, Tustin",
      "result": "win",
      "event_link": "https://boxrec.com/en/event/782636",
      "bout_link": "https://boxrec.com/en/event/782636/2331412"
    },
    {
      "date": "Dec 18",
      "opponent_name": "Marquis Valentine",
      "opponent_id": "768017",
      "opponent_url": "https://boxrec.com/en/box-pro/768017",
      "opponent_record": "5-4-0",
      "recent_form": "WLWLLL",
      "venue": "Industry Hills Expo Center, La Puente",
      "result": "win",
      "event_link": "https://boxrec.com/en/event/775977",
      "bout_link": "https://boxrec.com/en/event/775977/2303018"
    },
    {
      "date": "Oct 18",
      "opponent_name": "Tyrell Wright",
      "opponent_id": "622857",
      "opponent_url": "https://boxrec.com/en/box-pro/622857",
      "opponent_record": "9-2-2",
      "recent_form": "WWWDLL",
      "venue": "Madison Square Garden Theater, New York",
      "result": "win",
      "rating": 1,
      "event_link": "https://boxrec.com/en/event/773501",
      "bout_link": "https://boxrec.com/en/event/773501/2283489"
    },
    {
      "date": "Sep 18",
      "opponent_name": "Eduardo Vitela",
      "opponent_id": "759752",
      "opponent_url": "https://boxrec.com/en/box-pro/759752",
      "opponent_record": "3-2-0",
      "recent_form": "WWLLW",
      "venue": "Kings Theatre, Brooklyn",
      "result": "win",
      "event_link": "https://boxrec.com/en/event/774534",
      "bout_link": "https://boxrec.com/en/event/774534/2275469"
    },
    {
      "date": "May 18",
      "opponent_name": "Hugo Trujillo",
      "opponent_id": "639843",
      "opponent_url": "https://boxrec.com/en/box-pro/639843",
      "opponent_record": "4-0-1",
      "recent_form": "WDWWW",
      "venue": "Foxwoods Resort, Mashantucket",
      "result": "win",
      "rating": 1,
      "event_link": "https://boxrec.com/en/event/767452",
      "bout_link": "https://boxrec.com/en/event/767452/2247442"
    }
  ]
}